{
    "bloonEmissions_": [
        {
            "bloon": "Rainbow",
            "time": 0.0,
            "emissionIndex": 0
        },
        {
            "bloon": "Rainbow",
            "time": 34.2599983215332,
            "emissionIndex": 0
        },
        {
            "bloon": "Rainbow",
            "time": 68.5199966430664,
            "emissionIndex": 0
        },
        {
            "bloon": "Rainbow",
            "time": 102.77999877929688,
            "emissionIndex": 0
        },
        {
            "bloon": "Rainbow",
            "time": 137.0399932861328,
            "emissionIndex": 0
        }
    ],
    "score": 0.0,
    "bounds": [
        {
            "lowerBounds": 29,
            "upperBounds": 34
        }
    ]
}