{
    "bloonEmissions_": [
        {
            "bloon": "Ceramic",
            "time": 0.0,
            "emissionIndex": 0
        },
        {
            "bloon": "Ceramic",
            "time": 23.07176399230957,
            "emissionIndex": 0
        },
        {
            "bloon": "Ceramic",
            "time": 46.14352798461914,
            "emissionIndex": 0
        },
        {
            "bloon": "Ceramic",
            "time": 69.21529388427735,
            "emissionIndex": 0
        },
        {
            "bloon": "Ceramic",
            "time": 92.28705596923828,
            "emissionIndex": 0
        },
        {
            "bloon": "Ceramic",
            "time": 115.35881805419922,
            "emissionIndex": 0
        },
        {
            "bloon": "Ceramic",
            "time": 138.4305877685547,
            "emissionIndex": 0
        },
        {
            "bloon": "Ceramic",
            "time": 161.50234985351563,
            "emissionIndex": 0
        },
        {
            "bloon": "Ceramic",
            "time": 184.57411193847657,
            "emissionIndex": 0
        },
        {
            "bloon": "Ceramic",
            "time": 207.6458740234375,
            "emissionIndex": 0
        },
        {
            "bloon": "Ceramic",
            "time": 230.71763610839845,
            "emissionIndex": 0
        },
        {
            "bloon": "Ceramic",
            "time": 253.78939819335938,
            "emissionIndex": 0
        },
        {
            "bloon": "Ceramic",
            "time": 276.8611755371094,
            "emissionIndex": 0
        },
        {
            "bloon": "Ceramic",
            "time": 299.93292236328127,
            "emissionIndex": 0
        },
        {
            "bloon": "Ceramic",
            "time": 323.00469970703127,
            "emissionIndex": 0
        },
        {
            "bloon": "Ceramic",
            "time": 346.0764465332031,
            "emissionIndex": 0
        },
        {
            "bloon": "Ceramic",
            "time": 369.1482238769531,
            "emissionIndex": 0
        },
        {
            "bloon": "Ceramic",
            "time": 392.2200012207031,
            "emissionIndex": 0
        }
    ],
    "score": 0.0,
    "bounds": [
        {
            "lowerBounds": 33,
            "upperBounds": 45
        }
    ]
}