{
  "score": 0.0,
  "bounds": [
    {
      "lowerBounds": 24,
      "upperBounds": 28
    }
  ],
  "bloonEmissions": [
    {
      "bloon": "Zebra",
      "time": 0.0,
      "emissionIndex": 0,
      "name": "BloonEmissionModel_BloonGroupModel_Zebra x4 [24-28]",
      "ImplementationType": null
    },
    {
      "bloon": "Zebra",
      "time": 68.52,
      "emissionIndex": 0,
      "name": "BloonEmissionModel_BloonGroupModel_Zebra x4 [24-28]",
      "ImplementationType": null
    },
    {
      "bloon": "Zebra",
      "time": 137.04,
      "emissionIndex": 0,
      "name": "BloonEmissionModel_BloonGroupModel_Zebra x4 [24-28]",
      "ImplementationType": null
    },
    {
      "bloon": "Zebra",
      "time": 205.56,
      "emissionIndex": 0,
      "name": "BloonEmissionModel_BloonGroupModel_Zebra x4 [24-28]",
      "ImplementationType": null
    }
  ],
  "name": "FreeplayBloonGroupModel_Zebra x4 [24-28]",
  "ImplementationType": null
}